CB2325NumericaG1/__init__.py
CB2325NumericaG1/aproximacao/__init__.py
CB2325NumericaG1/aproximacao/aproximacao_regressao_exp_taylor.py
CB2325NumericaG1/aproximacao/aproximacao_trig_linear.py
CB2325NumericaG1/erros/__init__.py
CB2325NumericaG1/erros/erros.py
CB2325NumericaG1/estatistica/__init__.py
CB2325NumericaG1/estatistica/estatistica.py
CB2325NumericaG1/integracao/__init__.py
CB2325NumericaG1/integracao/integracao_estocastica.py
CB2325NumericaG1/integracao/integracao_trapezio_simpson13.py
CB2325NumericaG1/interpolacao/__init__.py
CB2325NumericaG1/interpolacao/interpolacao_linear.py
CB2325NumericaG1/interpolacao/interpolacao_polinomial.py
CB2325NumericaG1/interpolacao/interpolacao_polinomial_hermite.py
CB2325NumericaG1/interpolacao/interpolacao_polinomial_vandermond.py
CB2325NumericaG1/raizes/__init__.py
CB2325NumericaG1/raizes/raizes_bissecao.py
CB2325NumericaG1/raizes/raizes_newton_raphson.py
CB2325NumericaG1/raizes/raizes_secante.py
cb2325_numerica_g1-1.0.1.dist-info/METADATA
cb2325_numerica_g1-1.0.1.dist-info/WHEEL
cb2325_numerica_g1-1.0.1.dist-info/top_level.txt
cb2325_numerica_g1-1.0.1.dist-info/RECORD
