Metadata-Version: 2.4
Name: CB2325-numerica-G1
Version: 1.0.1
Summary: Biblioteca de cálculo numérico produzida pelos alunos do Grupo 1, para a disciplina de Programação 2, do IMPA Tech, ministrada pelo professor Emilio Vital Brazil..
Author: Alexander Kahleul, Cauan Carlos Rodrigues Dutra, Juan Martins Santos, Luana Fagundes De Lima, Luana Mognon Da Silva, Lucas Fraga Damasceno, Mariana Tiemi Yoshioka, Mateus Stacoviaki Galvão, Micaele Magalhães Brandão Veras, Rafael Augusto De Almeida, Ryan Carvalho Pereira Dos Santos
Author-email: al.alexander.kahleul@impatech.edu.br, al.cauan.dutra@impatech.edu.br, al.juan.santos@impatech.edu.br, al.luana.lima@impatech.edu.br, al.luana.silva@impatech.edu.br, al.lucas.damasceno@impatech.edu.br, al.mariana.yoshioka@impatech.edu.br, al.mateus.galvao@impatech.edu.br, al.micaele.veras@impatech.edu.br, al.rafael.almeida@impatech.edu.br, al.ryan.santos@impatech.edu.br
Project-URL: Código fonte, https://github.com/vrsmic/CB2325NumericaG1
Project-URL: Documentação, https://cb2325numericag1.readthedocs.io/pt-br/latest/
Requires-Python: >=3.10
Requires-Dist: numpy>=1.20.0
Requires-Dist: matplotlib
Requires-Dist: typing
Requires-Dist: sympy
Requires-Dist: setuptools
Dynamic: author
Dynamic: author-email
Dynamic: project-url
Dynamic: requires-dist
Dynamic: requires-python
Dynamic: summary
